pydantic_socketio/__init__.py
pydantic_socketio/fastapi_socketio.py
pydantic_socketio/py.typed
pydantic_socketio/pydantic_socketio.py
pydantic_socketio/types.py
pydantic_socketio-0.1.3.dist-info/METADATA
pydantic_socketio-0.1.3.dist-info/WHEEL
pydantic_socketio-0.1.3.dist-info/licenses/LICENSE
pydantic_socketio-0.1.3.dist-info/RECORD
