Metadata-Version: 2.4
Name: pydantic-socketio
Version: 0.1.3
Summary: Pydantic-enhanced SocketIO with FastAPI integration support.
Project-URL: homepage, https://github.com/atomiechen/Pydantic-SocketIO
Project-URL: issues, https://github.com/atomiechen/Pydantic-SocketIO/issues
Project-URL: changelog, https://github.com/atomiechen/Pydantic-SocketIO/blob/main/CHANGELOG.md
Author-email: Atomie CHEN <atomic_cwh@163.com>
License-File: LICENSE
Keywords: fastapi,pydantic,socketio
Classifier: License :: OSI Approved :: MIT License
Classifier: Operating System :: OS Independent
Classifier: Programming Language :: Python :: 3
Requires-Python: >=3.8
Requires-Dist: pydantic>=2.10.6
Requires-Dist: python-socketio>=5.12.1
Provides-Extra: asyncio-client
Requires-Dist: python-socketio[asyncio-client]>=5.12.1; extra == 'asyncio-client'
Provides-Extra: client
Requires-Dist: python-socketio[client]>=5.12.1; extra == 'client'
Provides-Extra: docs
Requires-Dist: python-socketio[docs]>=5.12.1; extra == 'docs'
Provides-Extra: fastapi
Requires-Dist: fastapi[standard]>=0.115.11; extra == 'fastapi'
